UART_test/Template/tmp/job_1/template.v
// Generator : SpinalHDL v1.8.1    git head : 2a7592004363e5b40ec43e1f122ed8641cd8965b
// Component : template
// Git hash  : 797233b64519f76c1edc9b8b144e1fa3f508c348

`timescale 1ns/1ps

module template (
  input               io_clk,
  input               io_rst_n,
  input               io_start,
  input      [7:0]    io_data,
  output              io_rs232_tx,
  output              io_done,
  input               clk,
  input               reset
);

  reg        [7:0]    clkarea_data_bat;
  reg                 clkarea_state;
  reg        [9:0]    clkarea_baud_cnt;
  wire                when_template_l46;
  reg                 clkarea_bit_flag;
  wire                when_template_l59;
  reg        [3:0]    clkarea_bit_cnt;
  wire                when_template_l70;
  reg                 clkarea_rx232_tx;
  reg                 clkarea_done;
  wire                when_template_l130;

  assign when_template_l46 = (clkarea_baud_cnt == 10'h0e9);
  assign when_template_l59 = (clkarea_baud_cnt == 10'h001);
  assign when_template_l70 = (clkarea_bit_cnt == 4'b1010);
  assign io_rs232_tx = clkarea_rx232_tx;
  assign when_template_l130 = (clkarea_bit_flag && (clkarea_bit_cnt == 4'b1010));
  assign io_done = clkarea_done;
  always @(posedge io_clk or negedge io_rst_n) begin
    if(!io_rst_n) begin
      clkarea_data_bat <= 8'h0;
      clkarea_state <= 1'b0;
      clkarea_baud_cnt <= 10'h0;
      clkarea_bit_flag <= 1'b0;
      clkarea_bit_cnt <= 4'b0000;
      clkarea_rx232_tx <= 1'b0;
      clkarea_done <= 1'b0;
    end else begin
      if(io_start) begin
        clkarea_data_bat <= io_data;
      end else begin
        clkarea_data_bat <= clkarea_data_bat;
      end
      if(io_start) begin
        clkarea_state <= 1'b1;
      end else begin
        if(io_done) begin
          clkarea_state <= 1'b0;
        end else begin
          clkarea_state <= clkarea_state;
        end
      end
      if(clkarea_state) begin
        if(when_template_l46) begin
          clkarea_baud_cnt <= 10'h0;
        end else begin
          clkarea_baud_cnt <= (clkarea_baud_cnt + 10'h001);
        end
      end else begin
        clkarea_baud_cnt <= 10'h0;
      end
      if(when_template_l59) begin
        clkarea_bit_flag <= 1'b1;
      end else begin
        clkarea_bit_flag <= 1'b0;
      end
      if(clkarea_bit_flag) begin
        if(when_template_l70) begin
          clkarea_bit_cnt <= 4'b0000;
        end else begin
          clkarea_bit_cnt <= (clkarea_bit_cnt + 4'b0001);
        end
      end else begin
        clkarea_bit_cnt <= clkarea_bit_cnt;
      end
      if(clkarea_state) begin
        if(clkarea_bit_flag) begin
          case(clkarea_bit_cnt)
            4'b0000 : begin
              clkarea_rx232_tx <= 1'b0;
            end
            4'b0001 : begin
              clkarea_rx232_tx <= clkarea_data_bat[0];
            end
            4'b0010 : begin
              clkarea_rx232_tx <= clkarea_data_bat[1];
            end
            4'b0011 : begin
              clkarea_rx232_tx <= clkarea_data_bat[2];
            end
            4'b0100 : begin
              clkarea_rx232_tx <= clkarea_data_bat[3];
            end
            4'b0101 : begin
              clkarea_rx232_tx <= clkarea_data_bat[4];
            end
            4'b0110 : begin
              clkarea_rx232_tx <= clkarea_data_bat[5];
            end
            4'b0111 : begin
              clkarea_rx232_tx <= clkarea_data_bat[6];
            end
            4'b1000 : begin
              clkarea_rx232_tx <= clkarea_data_bat[7];
            end
            4'b1001 : begin
              clkarea_rx232_tx <= 1'b1;
            end
            default : begin
              clkarea_rx232_tx <= 1'b1;
            end
          endcase
        end
      end else begin
        clkarea_rx232_tx <= 1'b1;
      end
      if(when_template_l130) begin
        clkarea_done <= 1'b1;
      end else begin
        clkarea_done <= 1'b0;
      end
    end
  end


endmodule

UART_test/Template/simWorkspace/template/test.vcd
$version Generated by VerilatedVcd $end
$timescale 1ps $end

 $scope module TOP $end
  $var wire  1 4 clk $end
  $var wire  1 . io_clk $end
  $var wire  8 1 io_data [7:0] $end
  $var wire  1 3 io_done $end
  $var wire  1 2 io_rs232_tx $end
  $var wire  1 / io_rst_n $end
  $var wire  1 0 io_start $end
  $var wire  1 5 reset $end
  $scope module template $end
   $var wire  1 4 clk $end
   $var wire 10 % clkarea_baud_cnt [9:0] $end
   $var wire  4 ) clkarea_bit_cnt [3:0] $end
   $var wire  1 ' clkarea_bit_flag $end
   $var wire  8 # clkarea_data_bat [7:0] $end
   $var wire  1 , clkarea_done $end
   $var wire  1 + clkarea_rx232_tx $end
   $var wire  1 $ clkarea_state $end
   $var wire  1 . io_clk $end
   $var wire  8 1 io_data [7:0] $end
   $var wire  1 3 io_done $end
   $var wire  1 2 io_rs232_tx $end
   $var wire  1 / io_rst_n $end
   $var wire  1 0 io_start $end
   $var wire  1 5 reset $end
   $var wire  1 - when_template_l130 $end
   $var wire  1 & when_template_l46 $end
   $var wire  1 ( when_template_l59 $end
   $var wire  1 * when_template_l70 $end
  $upscope $end
 $upscope $end
$enddefinitions $end


#0
b00000000 #
0$
b0000000000 %
0&
0'
0(
b0000 )
0*
0+
0,
0-
0.
0/
00
b00101001 1
02
03
04
15
#160
1/
#170
1+
1.
12
#175
0.
#180
1.
#185
0.
#190
1.
#195
0.
#200
b00110111 #
1$
1.
10
b00110111 1
#205
0.
#210
b0000000001 %
1(
1.
#215
0.
#220
b0000000010 %
1'
0(
1.
00
#225
0.
#230
b0000000011 %
0'
b0001 )
0+
1.
02
#235
0.
#240
b0000000100 %
1.
#245
0.
#250
b0000000101 %
1.
#255
0.
#260
b0000000110 %
1.
#265
0.
#270
b0000000111 %
1.
#275
0.
#280
b0000001000 %
1.
#285
0.
#290
b0000001001 %
1.
#295
0.
#300
b0000001010 %
1.
#305
0.
#310
b0000001011 %
1.
#315
0.
#320
b0000001100 %
1.
#325
0.
#330
b0000001101 %
1.
#335
0.
#340
b0000001110 %
1.
#345
0.
#350
b0000001111 %
1.
#355
0.
#360
b0000010000 %
1.
#365
0.
#370
b0000010001 %
1.
#375
0.
#380
b0000010010 %
1.
#385
0.
#390
b0000010011 %
1.
#395
0.
#400
b0000010100 %
1.
#405
0.
#410
b0000010101 %
1.
#415
0.
#420
b0000010110 %
1.
#425
0.
#430
b0000010111 %
1.
#435
0.
#440
b0000011000 %
1.
#445
0.
#450
b0000011001 %
1.
#455
0.
#460
b0000011010 %
1.
#465
0.
#470
b0000011011 %
1.
#475
0.
#480
b0000011100 %
1.
#485
0.
#490
b0000011101 %
1.
#495
0.
#500
b0000011110 %
1.
#505
0.
#510
b0000011111 %
1.
#515
0.
#520
b0000100000 %
1.
#525
0.
#530
b0000100001 %
1.
#535
0.
#540
b0000100010 %
1.
#545
0.
#550
b0000100011 %
1.
#555
0.
#560
b0000100100 %
1.
#565
0.
#570
b0000100101 %
1.
#575
0.
#580
b0000100110 %
1.
#585
0.
#590
b0000100111 %
1.
#595
0.
#600
b0000101000 %
1.
#605
0.
#610
b0000101001 %
1.
#615
0.
#620
b0000101010 %
1.
#625
0.
#630
b0000101011 %
1.
#635
0.
#640
b0000101100 %
1.
#645
0.
#650
b0000101101 %
1.
#655
0.
#660
b0000101110 %
1.
#665
0.
#670
b0000101111 %
1.
#675
0.
#680
b0000110000 %
1.
#685
0.
#690
b0000110001 %
1.
#695
0.
#700
b0000110010 %
1.
#705
0.
#710
b0000110011 %
1.
#715
0.
#720
b0000110100 %
1.
#725
0.
#730
b0000110101 %
1.
#735
0.
#740
b0000110110 %
1.
#745
0.
#750
b0000110111 %
1.
#755
0.
#760
b0000111000 %
1.
#765
0.
#770
b0000111001 %
1.
#775
0.
#780
b0000111010 %
1.
#785
0.
#790
b0000111011 %
1.
#795
0.
#800
b0000111100 %
1.
#805
0.
#810
b0000111101 %
1.
#815
0.
#820
b0000111110 %
1.
#825
0.
#830
b0000111111 %
1.
#835
0.
#840
b0001000000 %
1.
#845
0.
#850
b0001000001 %
1.
#855
0.
#860
b0001000010 %
1.
#865
0.
#870
b0001000011 %
1.
#875
0.
#880
b0001000100 %
1.
#885
0.
#890
b0001000101 %
1.
#895
0.
#900
b0001000110 %
1.
#905
0.
#910
b0001000111 %
1.
#915
0.
#920
b0001001000 %
1.
#925
0.
#930
b0001001001 %
1.
#935
0.
#940
b0001001010 %
1.
#945
0.
#950
b0001001011 %
1.
#955
0.
#960
b0001001100 %
1.
#965
0.
#970
b0001001101 %
1.
#975
0.
#980
b0001001110 %
1.
#985
0.
#990
b0001001111 %
1.
#995
0.
#1000
b0001010000 %
1.
#1005
0.
#1010
b0001010001 %
1.
#1015
0.
#1020
b0001010010 %
1.
#1025
0.
#1030
b0001010011 %
1.
#1035
0.
#1040
b0001010100 %
1.
#1045
0.
#1050
b0001010101 %
1.
#1055
0.
#1060
b0001010110 %
1.
#1065
0.
#1070
b0001010111 %
1.
#1075
0.
#1080
b0001011000 %
1.
#1085
0.
#1090
b0001011001 %
1.
#1095
0.
#1100
b0001011010 %
1.
#1105
0.
#1110
b0001011011 %
1.
#1115
0.
#1120
b0001011100 %
1.
#1125
0.
#1130
b0001011101 %
1.
#1135
0.
#1140
b0001011110 %
1.
#1145
0.
#1150
b0001011111 %
1.
#1155
0.
#1160
b0001100000 %
1.
#1165
0.
#1170
b0001100001 %
1.
#1175
0.
#1180
b0001100010 %
1.
#1185
0.
#1190
b0001100011 %
1.
#1195
0.
#1200
b0001100100 %
1.
#1205
0.
#1210
b0001100101 %
1.
#1215
0.
#1220
b0001100110 %
1.
#1225
0.
#1230
b0001100111 %
1.
#1235
0.
#1240
b0001101000 %
1.
#1245
0.
#1250
b0001101001 %
1.
#1255
0.
#1260
b0001101010 %
1.
#1265
0.
#1270
b0001101011 %
1.
#1275
0.
#1280
b0001101100 %
1.
#1285
0.
#1290
b0001101101 %
1.
#1295
0.
#1300
b0001101110 %
1.
#1305
0.
#1310
b0001101111 %
1.
#1315
0.
#1320
b0001110000 %
1.
#1325
0.
#1330
b0001110001 %
1.
#1335
0.
#1340
b0001110010 %
1.
#1345
0.
#1350
b0001110011 %
1.
#1355
0.
#1360
b0001110100 %
1.
#1365
0.
#1370
b0001110101 %
1.
#1375
0.
#1380
b0001110110 %
1.
#1385
0.
#1390
b0001110111 %
1.
#1395
0.
#1400
b0001111000 %
1.
#1405
0.
#1410
b0001111001 %
1.
#1415
0.
#1420
b0001111010 %
1.
#1425
0.
#1430
b0001111011 %
1.
#1435
0.
#1440
b0001111100 %
1.
#1445
0.
#1450
b0001111101 %
1.
#1455
0.
#1460
b0001111110 %
1.
#1465
0.
#1470
b0001111111 %
1.
#1475
0.
#1480
b0010000000 %
1.
#1485
0.
#1490
b0010000001 %
1.
#1495
0.
#1500
b0010000010 %
1.
#1505
0.
#1510
b0010000011 %
1.
#1515
0.
#1520
b0010000100 %
1.
#1525
0.
#1530
b0010000101 %
1.
#1535
0.
#1540
b0010000110 %
1.
#1545
0.
#1550
b0010000111 %
1.
#1555
0.
#1560
b0010001000 %
1.
#1565
0.
#1570
b0010001001 %
1.
#1575
0.
#1580
b0010001010 %
1.
#1585
0.
#1590
b0010001011 %
1.
#1595
0.
#1600
b0010001100 %
1.
#1605
0.
#1610
b0010001101 %
1.
#1615
0.
#1620
b0010001110 %
1.
#1625
0.
#1630
b0010001111 %
1.
#1635
0.
#1640
b0010010000 %
1.
#1645
0.
#1650
b0010010001 %
1.
#1655
0.
#1660
b0010010010 %
1.
#1665
0.
#1670
b0010010011 %
1.
#1675
0.
#1680
b0010010100 %
1.
#1685
0.
#1690
b0010010101 %
1.
#1695
0.
#1700
b0010010110 %
1.
#1705
0.
#1710
b0010010111 %
1.
#1715
0.
#1720
b0010011000 %
1.
#1725
0.
#1730
b0010011001 %
1.
#1735
0.
#1740
b0010011010 %
1.
#1745
0.
#1750
b0010011011 %
1.
#1755
0.
#1760
b0010011100 %
1.
#1765
0.
#1770
b0010011101 %
1.
#1775
0.
#1780
b0010011110 %
1.
#1785
0.
#1790
b0010011111 %
1.
#1795
0.
#1800
b0010100000 %
1.
#1805
0.
#1810
b0010100001 %
1.
#1815
0.
#1820
b0010100010 %
1.
#1825
0.
#1830
b0010100011 %
1.
#1835
0.
#1840
b0010100100 %
1.
#1845
0.
#1850
b0010100101 %
1.
#1855
0.
#1860
b0010100110 %
1.
#1865
0.
#1870
b0010100111 %
1.
#1875
0.
#1880
b0010101000 %
1.
#1885
0.
#1890
b0010101001 %
1.
#1895
0.
#1900
b0010101010 %
1.
#1905
0.
#1910
b0010101011 %
1.
#1915
0.
#1920
b0010101100 %
1.
#1925
0.
#1930
b0010101101 %
1.
#1935
0.
#1940
b0010101110 %
1.
#1945
0.
#1950
b0010101111 %
1.
#1955
0.
#1960
b0010110000 %
1.
#1965
0.
#1970
b0010110001 %
1.
#1975
0.
#1980
b0010110010 %
1.
#1985
0.
#1990
b0010110011 %
1.
#1995
0.
#2000
b0010110100 %
1.
#2005
0.
#2010
b0010110101 %
1.
#2015
0.
#2020
b0010110110 %
1.
#2025
0.
#2030
b0010110111 %
1.
#2035
0.
#2040
b0010111000 %
1.
#2045
0.
#2050
b0010111001 %
1.
#2055
0.
#2060
b0010111010 %
1.
#2065
0.
#2070
b0010111011 %
1.
#2075
0.
#2080
b0010111100 %
1.
#2085
0.
#2090
b0010111101 %
1.
#2095
0.
#2100
b0010111110 %
1.
#2105
0.
#2110
b0010111111 %
1.
#2115
0.
#2120
b0011000000 %
1.
#2125
0.
#2130
b0011000001 %
1.
#2135
0.
#2140
b0011000010 %
1.
#2145
0.
#2150
b0011000011 %
1.
#2155
0.
#2160
b0011000100 %
1.
#2165
0.
#2170
b0011000101 %
1.
#2175
0.
#2180
b0011000110 %
1.
#2185
0.
#2190
b0011000111 %
1.
#2195
0.
#2200
b0011001000 %
1.
#2205
0.
#2210
b0011001001 %
1.
#2215
0.
#2220
b0011001010 %
1.
#2225
0.
#2230
b0011001011 %
1.
#2235
0.
#2240
b0011001100 %
1.
#2245
0.
#2250
b0011001101 %
1.
#2255
0.
#2260
b0011001110 %
1.
#2265
0.
#2270
b0011001111 %
1.
#2275
0.
#2280
b0011010000 %
1.
#2285
0.
#2290
b0011010001 %
1.
#2295
0.
#2300
b0011010010 %
1.
#2305
0.
#2310
b0011010011 %
1.
#2315
0.
#2320
b0011010100 %
1.
#2325
0.
#2330
b0011010101 %
1.
#2335
0.
#2340
b0011010110 %
1.
#2345
0.
#2350
b0011010111 %
1.
#2355
0.
#2360
b0011011000 %
1.
#2365
0.
#2370
b0011011001 %
1.
#2375
0.
#2380
b0011011010 %
1.
#2385
0.
#2390
b0011011011 %
1.
#2395
0.
#2400
b0011011100 %
1.
#2405
0.
#2410
b0011011101 %
1.
#2415
0.
#2420
b0011011110 %
1.
#2425
0.
#2430
b0011011111 %
1.
#2435
0.
#2440
b0011100000 %
1.
#2445
0.
#2450
b0011100001 %
1.
#2455
0.
#2460
b0011100010 %
1.
#2465
0.
#2470
b0011100011 %
1.
#2475
0.
#2480
b0011100100 %
1.
#2485
0.
#2490
b0011100101 %
1.
#2495
0.
#2500
b0011100110 %
1.
#2505
0.
#2510
b0011100111 %
1.
#2515
0.
#2520
b0011101000 %
1.
#2525
0.
#2530
b0011101001 %
1&
1.
#2535
0.
#2540
b0000000000 %
0&
1.
#2545
0.
#2550
b0000000001 %
1(
1.
#2555
0.
#2560
b0000000010 %
1'
0(
1.
#2565
0.
#2570
b0000000011 %
0'
b0010 )
1+
1.
12
#2575
0.
#2580
b0000000100 %
1.
#2585
0.
#2590
b0000000101 %
1.
#2595
0.
#2600
b0000000110 %
1.
#2605
0.
#2610
b0000000111 %
1.
#2615
0.
#2620
b0000001000 %
1.
#2625
0.
#2630
b0000001001 %
1.
#2635
0.
#2640
b0000001010 %
1.
#2645
0.
#2650
b0000001011 %
1.
#2655
0.
#2660
b0000001100 %
1.
#2665
0.
#2670
b0000001101 %
1.
#2675
0.
#2680
b0000001110 %
1.
#2685
0.
#2690
b0000001111 %
1.
#2695
0.
#2700
b0000010000 %
1.
#2705
0.
#2710
b0000010001 %
1.
#2715
0.
#2720
b0000010010 %
1.
#2725
0.
#2730
b0000010011 %
1.
#2735
0.
#2740
b0000010100 %
1.
#2745
0.
#2750
b0000010101 %
1.
#2755
0.
#2760
b0000010110 %
1.
#2765
0.
#2770
b0000010111 %
1.
#2775
0.
#2780
b0000011000 %
1.
#2785
0.
#2790
b0000011001 %
1.
#2795
0.
#2800
b0000011010 %
1.
#2805
0.
#2810
b0000011011 %
1.
#2815
0.
#2820
b0000011100 %
1.
#2825
0.
#2830
b0000011101 %
1.
#2835
0.
#2840
b0000011110 %
1.
#2845
0.
#2850
b0000011111 %
1.
#2855
0.
#2860
b0000100000 %
1.
#2865
0.
#2870
b0000100001 %
1.
#2875
0.
#2880
b0000100010 %
1.
#2885
0.
#2890
b0000100011 %
1.
#2895
0.
#2900
b0000100100 %
1.
#2905
0.
#2910
b0000100101 %
1.
#2915
0.
#2920
b0000100110 %
1.
#2925
0.
#2930
b0000100111 %
1.
#2935
0.
#2940
b0000101000 %
1.
#2945
0.
#2950
b0000101001 %
1.
#2955
0.
#2960
b0000101010 %
1.
#2965
0.
#2970
b0000101011 %
1.
#2975
0.
#2980
b0000101100 %
1.
#2985
0.
#2990
b0000101101 %
1.
#2995
0.
#3000
b0000101110 %
1.
#3005
0.
#3010
b0000101111 %
1.
#3015
0.
#3020
b0000110000 %
1.
#3025
0.
#3030
b0000110001 %
1.
#3035
0.
#3040
b0000110010 %
1.
#3045
0.
#3050
b0000110011 %
1.
#3055
0.
#3060
b0000110100 %
1.
#3065
0.
#3070
b0000110101 %
1.
#3075
0.
#3080
b0000110110 %
1.
#3085
0.
#3090
b0000110111 %
1.
#3095
0.
#3100
b0000111000 %
1.
#3105
0.
#3110
b0000111001 %
1.
#3115
0.
#3120
b0000111010 %
1.
#3125
0.
#3130
b0000111011 %
1.
#3135
0.
#3140
b0000111100 %
1.
#3145
0.
#3150
b0000111101 %
1.
#3155
0.
#3160
b0000111110 %
1.
#3165
0.
#3170
b0000111111 %
1.
#3175
0.
#3180
b0001000000 %
1.
#3185
0.
#3190
b0001000001 %
1.
#3195
0.
#3200
b0001000010 %
1.
#3205
0.
#3210
b0001000011 %
1.
#3215
0.
#3220
b0001000100 %
1.
#3225
0.
#3230
b0001000101 %
1.
#3235
0.
#3240
b0001000110 %
1.
#3245
0.
#3250
b0001000111 %
1.
#3255
0.
#3260
b0001001000 %
1.
#3265
0.
#3270
b0001001001 %
1.
#3275
0.
#3280
b0001001010 %
1.
#3285
0.
#3290
b0001001011 %
1.
#3295
0.
#3300
b0001001100 %
1.
#3305
0.
#3310
b0001001101 %
1.
#3315
0.
#3320
b0001001110 %
1.
#3325
0.
#3330
b0001001111 %
1.
#3335
0.
#3340
b0001010000 %
1.
#3345
0.
#3350
b0001010001 %
1.
#3355
0.
#3360
b0001010010 %
1.
#3365
0.
#3370
b0001010011 %
1.
#3375
0.
#3380
b0001010100 %
1.
#3385
0.
#3390
b0001010101 %
1.
#3395
0.
#3400
b0001010110 %
1.
#3405
0.
#3410
b0001010111 %
1.
#3415
0.
#3420
b0001011000 %
1.
#3425
0.
#3430
b0001011001 %
1.
#3435
0.
#3440
b0001011010 %
1.
#3445
0.
#3450
b0001011011 %
1.
#3455
0.
#3460
b0001011100 %
1.
#3465
0.
#3470
b0001011101 %
1.
#3475
0.
#3480
b0001011110 %
1.
#3485
0.
#3490
b0001011111 %
1.
#3495
0.
#3500
b0001100000 %
1.
#3505
0.
#3510
b0001100001 %
1.
#3515
0.
#3520
b0001100010 %
1.
#3525
0.
#3530
b0001100011 %
1.
#3535
0.
#3540
b0001100100 %
1.
#3545
0.
#3550
b0001100101 %
1.
#3555
0.
#3560
b0001100110 %
1.
#3565
0.
#3570
b0001100111 %
1.
#3575
0.
#3580
b0001101000 %
1.
#3585
0.
#3590
b0001101001 %
1.
#3595
0.
#3600
b0001101010 %
1.
#3605
0.
#3610
b0001101011 %
1.
#3615
0.
#3620
b0001101100 %
1.
#3625
0.
#3630
b0001101101 %
1.
#3635
0.
#3640
b0001101110 %
1.
#3645
0.
#3650
b0001101111 %
1.
#3655
0.
#3660
b0001110000 %
1.
#3665
0.
#3670
b0001110001 %
1.
#3675
0.
#3680
b0001110010 %
1.
#3685
0.
#3690
b0001110011 %
1.
#3695
0.
#3700
b0001110100 %
1.
#3705
0.
#3710
b0001110101 %
1.
#3715
0.
#3720
b0001110110 %
1.
#3725
0.
#3730
b0001110111 %
1.
#3735
0.
#3740
b0001111000 %
1.
#3745
0.
#3750
b0001111001 %
1.
#3755
0.
#3760
b0001111010 %
1.
#3765
0.
#3770
b0001111011 %
1.
#3775
0.
#3780
b0001111100 %
1.
#3785
0.
#3790
b0001111101 %
1.
#3795
0.
#3800
b0001111110 %
1.
#3805
0.
#3810
b0001111111 %
1.
#3815
0.
#3820
b0010000000 %
1.
#3825
0.
#3830
b0010000001 %
1.
#3835
0.
#3840
b0010000010 %
1.
#3845
0.
#3850
b0010000011 %
1.
#3855
0.
#3860
b0010000100 %
1.
#3865
0.
#3870
b0010000101 %
1.
#3875
0.
#3880
b0010000110 %
1.
#3885
0.
#3890
b0010000111 %
1.
#3895
0.
#3900
b0010001000 %
1.
#3905
0.
#3910
b0010001001 %
1.
#3915
0.
#3920
b0010001010 %
1.
#3925
0.
#3930
b0010001011 %
1.
#3935
0.
#3940
b0010001100 %
1.
#3945
0.
#3950
b0010001101 %
1.
#3955
0.
#3960
b0010001110 %
1.
#3965
0.
#3970
b0010001111 %
1.
#3975
0.
#3980
b0010010000 %
1.
#3985
0.
#3990
b0010010001 %
1.
#3995
0.
#4000
b0010010010 %
1.
#4005
0.
#4010
b0010010011 %
1.
#4015
0.
#4020
b0010010100 %
1.
#4025
0.
#4030
b0010010101 %
1.
#4035
0.
#4040
b0010010110 %
1.
#4045
0.
#4050
b0010010111 %
1.
#4055
0.
#4060
b0010011000 %
1.
#4065
0.
#4070
b0010011001 %
1.
#4075
0.
#4080
b0010011010 %
1.
#4085
0.
#4090
b0010011011 %
1.
#4095
0.
#4100
b0010011100 %
1.
#4105
0.
#4110
b0010011101 %
1.
#4115
0.
#4120
b0010011110 %
1.
#4125
0.
#4130
b0010011111 %
1.
#4135
0.
#4140
b0010100000 %
1.
#4145
0.
#4150
b0010100001 %
1.
#4155
0.
#4160
b0010100010 %
1.
#4165
0.
#4170
b0010100011 %
1.
#4175
0.
#4180
b0010100100 %
1.
#4185
0.
#4190
b0010100101 %
1.
#4195
0.
#4200
b0010100110 %
1.
#4205
0.
#4210
b0010100111 %
1.
#4215
0.
#4220
b0010101000 %
1.
#4225
0.
#4230
b0010101001 %
1.
#4235
0.
#4240
b0010101010 %
1.
#4245
0.
#4250
b0010101011 %
1.
#4255
0.
#4260
b0010101100 %
1.
#4265
0.
#4270
b0010101101 %
1.
#4275
0.
#4280
b0010101110 %
1.
#4285
0.
#4290
b0010101111 %
1.
#4295
0.
#4300
b0010110000 %
1.
#4305
0.
#4310
b0010110001 %
1.
#4315
0.
#4320
b0010110010 %
1.
#4325
0.
#4330
b0010110011 %
1.
#4335
0.
#4340
b0010110100 %
1.
#4345
0.
#4350
b0010110101 %
1.
#4355
0.
#4360
b0010110110 %
1.
#4365
0.
#4370
b0010110111 %
1.
#4375
0.
#4380
b0010111000 %
1.
#4385
0.
#4390
b0010111001 %
1.
#4395
0.
#4400
b0010111010 %
1.
#4405
0.
#4410
b0010111011 %
1.
#4415
0.
#4420
b0010111100 %
1.
#4425
0.
#4430
b0010111101 %
1.
#4435
0.
#4440
b0010111110 %
1.
#4445
0.
#4450
b0010111111 %
1.
#4455
0.
#4460
b0011000000 %
1.
#4465
0.
#4470
b0011000001 %
1.
#4475
0.
#4480
b0011000010 %
1.
#4485
0.
#4490
b0011000011 %
1.
#4495
0.
#4500
b0011000100 %
1.
#4505
0.
#4510
b0011000101 %
1.
#4515
0.
#4520
b0011000110 %
1.
#4525
0.
#4530
b0011000111 %
1.
#4535
0.
#4540
b0011001000 %
1.
#4545
0.
#4550
b0011001001 %
1.
#4555
0.
#4560
b0011001010 %
1.
#4565
0.
#4570
b0011001011 %
1.
#4575
0.
#4580
b0011001100 %
1.
#4585
0.
#4590
b0011001101 %
1.
#4595
0.
#4600
b0011001110 %
1.
#4605
0.
#4610
b0011001111 %
1.
#4615
0.
#4620
b0011010000 %
1.
#4625
0.
#4630
b0011010001 %
1.
#4635
0.
#4640
b0011010010 %
1.
#4645
0.
#4650
b0011010011 %
1.
#4655
0.
#4660
b0011010100 %
1.
#4665
0.
#4670
b0011010101 %
1.
#4675
0.
#4680
b0011010110 %
1.
#4685
0.
#4690
b0011010111 %
1.
#4695
0.
#4700
b0011011000 %
1.
#4705
0.
#4710
b0011011001 %
1.
#4715
0.
#4720
b0011011010 %
1.
#4725
0.
#4730
b0011011011 %
1.
#4735
0.
#4740
b0011011100 %
1.
#4745
0.
#4750
b0011011101 %
1.
#4755
0.
#4760
b0011011110 %
1.
#4765
0.
#4770
b0011011111 %
1.
#4775
0.
#4780
b0011100000 %
1.
#4785
0.
#4790
b0011100001 %
1.
#4795
0.
#4800
b0011100010 %
1.
#4805
0.
#4810
b0011100011 %
1.
#4815
0.
#4820
b0011100100 %
1.
#4825
0.
#4830
b0011100101 %
1.
#4835
0.
#4840
b0011100110 %
1.
#4845
0.
#4850
b0011100111 %
1.
#4855
0.
#4860
b0011101000 %
1.
#4865
0.
#4870
b0011101001 %
1&
1.
#4875
0.
#4880
b0000000000 %
0&
1.
#4885
0.
#4890
b0000000001 %
1(
1.
#4895
0.
#4900
b0000000010 %
1'
0(
1.
#4905
0.
#4910
b0000000011 %
0'
b0011 )
1.
#4915
0.
#4920
b0000000100 %
1.
#4925
0.
#4930
b0000000101 %
1.
#4935
0.
#4940
b0000000110 %
1.
#4945
0.
#4950
b0000000111 %
1.
#4955
0.
#4960
b0000001000 %
1.
#4965
0.
#4970
b0000001001 %
1.
#4975
0.
#4980
b0000001010 %
1.
#4985
0.
#4990
b0000001011 %
1.
#4995
0.
#5000
b0000001100 %
1.
#5005
0.
#5010
b0000001101 %
1.
#5015
0.
#5020
b0000001110 %
1.
#5025
0.
#5030
b0000001111 %
1.
#5035
0.
#5040
b0000010000 %
1.
#5045
0.
#5050
b0000010001 %
1.
#5055
0.
#5060
b0000010010 %
1.
#5065
0.
#5070
b0000010011 %
1.
#5075
0.
#5080
b0000010100 %
1.
#5085
0.
#5090
b0000010101 %
1.
#5095
0.
#5100
b0000010110 %
1.
#5105
0.
#5110
b0000010111 %
1.
#5115
0.
#5120
b0000011000 %
1.
#5125
0.
#5130
b0000011001 %
1.
#5135
0.
#5140
b0000011010 %
1.
#5145
0.
#5150
b0000011011 %
1.
#5155
0.
#5160
b0000011100 %
1.
#5165
0.
#5170
b0000011101 %
1.
#5175
0.
#5180
b0000011110 %
1.
#5185
0.
#5190
b0000011111 %
1.
#5195
0.
#5200
b0000100000 %
1.
#5205
0.
#5210
b0000100001 %
1.
#5215
0.
#5220
b0000100010 %
1.
#5225
0.
#5230
b0000100011 %
1.
#5235
0.
#5240
b0000100100 %
1.
#5245
0.
#5250
b0000100101 %
1.
#5255
0.
#5260
b0000100110 %
1.
#5265
0.
#5270
b0000100111 %
1.
#5275
0.
#5280
b0000101000 %
1.
#5285
0.
#5290
b0000101001 %
1.
#5295
0.
#5300
b0000101010 %
1.
#5305
0.
#5310
b0000101011 %
1.
#5315
0.
#5320
b0000101100 %
1.
#5325
0.
#5330
b0000101101 %
1.
#5335
0.
#5340
b0000101110 %
1.
#5345
0.
#5350
b0000101111 %
1.
#5355
0.
#5360
b0000110000 %
1.
#5365
0.
#5370
b0000110001 %
1.
#5375
0.
#5380
b0000110010 %
1.
#5385
0.
#5390
b0000110011 %
1.
#5395
0.
#5400
b0000110100 %
1.
#5405
0.
#5410
b0000110101 %
1.
#5415
0.
#5420
b0000110110 %
1.
#5425
0.
#5430
b0000110111 %
1.
#5435
0.
#5440
b0000111000 %
1.
#5445
0.
#5450
b0000111001 %
1.
#5455
0.
#5460
b0000111010 %
1.
#5465
0.
#5470
b0000111011 %
1.
#5475
0.
#5480
b0000111100 %
1.
#5485
0.
#5490
b0000111101 %
1.
#5495
0.
#5500
b0000111110 %
1.
#5505
0.
#5510
b0000111111 %
1.
#5515
0.
#5520
b0001000000 %
1.
#5525
0.
#5530
b0001000001 %
1.
#5535
0.
#5540
b0001000010 %
1.
#5545
0.
#5550
b0001000011 %
1.
#5555
0.
#5560
b0001000100 %
1.
#5565
0.
#5570
b0001000101 %
1.
#5575
0.
#5580
b0001000110 %
1.
#5585
0.
#5590
b0001000111 %
1.
#5595
0.
#5600
b0001001000 %
1.
#5605
0.
#5610
b0001001001 %
1.
#5615
0.
#5620
b0001001010 %
1.
#5625
0.
#5630
b0001001011 %
1.
#5635
0.
#5640
b0001001100 %
1.
#5645
0.
#5650
b0001001101 %
1.
#5655
0.
#5660
b0001001110 %
1.
#5665
0.
#5670
b0001001111 %
1.
#5675
0.
#5680
b0001010000 %
1.
#5685
0.
#5690
b0001010001 %
1.
#5695
0.
#5700
b0001010010 %
1.
#5705
0.
#5710
b0001010011 %
1.
#5715
0.
#5720
b0001010100 %
1.
#5725
0.
#5730
b0001010101 %
1.
#5735
0.
#5740
b0001010110 %
1.
#5745
0.
#5750
b0001010111 %
1.
#5755
0.
#5760
b0001011000 %
1.
#5765
0.
#5770
b0001011001 %
1.
#5775
0.
#5780
b0001011010 %
1.
#5785
0.
#5790
b0001011011 %
1.
#5795
0.
#5800
b0001011100 %
1.
#5805
0.
#5810
b0001011101 %
1.
#5815
0.
#5820
b0001011110 %
1.
#5825
0.
#5830
b0001011111 %
1.
#5835
0.
#5840
b0001100000 %
1.
#5845
0.
#5850
b0001100001 %
1.
#5855
0.
#5860
b0001100010 %
1.
#5865
0.
#5870
b0001100011 %
1.
#5875
0.
#5880
b0001100100 %
1.
#5885
0.
#5890
b0001100101 %
1.
#5895
0.
#5900
b0001100110 %
1.
